odoo/addons/partner_risk_insurance_product_sticker_invoice_report/README.rst
odoo/addons/partner_risk_insurance_product_sticker_invoice_report/__init__.py
odoo/addons/partner_risk_insurance_product_sticker_invoice_report/__manifest__.py
odoo/addons/partner_risk_insurance_product_sticker_invoice_report/i18n/es.po
odoo/addons/partner_risk_insurance_product_sticker_invoice_report/i18n/it.po
odoo/addons/partner_risk_insurance_product_sticker_invoice_report/i18n/partner_risk_insurance_product_sticker_invoice_report.pot
odoo/addons/partner_risk_insurance_product_sticker_invoice_report/models/__init__.py
odoo/addons/partner_risk_insurance_product_sticker_invoice_report/models/account_move.py
odoo/addons/partner_risk_insurance_product_sticker_invoice_report/models/credit_policy_company.py
odoo/addons/partner_risk_insurance_product_sticker_invoice_report/models/product_sticker.py
odoo/addons/partner_risk_insurance_product_sticker_invoice_report/readme/CONFIGURE.md
odoo/addons/partner_risk_insurance_product_sticker_invoice_report/readme/CONTEXT.md
odoo/addons/partner_risk_insurance_product_sticker_invoice_report/readme/CONTRIBUTORS.md
odoo/addons/partner_risk_insurance_product_sticker_invoice_report/readme/DESCRIPTION.md
odoo/addons/partner_risk_insurance_product_sticker_invoice_report/readme/USAGE.md
odoo/addons/partner_risk_insurance_product_sticker_invoice_report/static/description/icon.png
odoo/addons/partner_risk_insurance_product_sticker_invoice_report/static/description/index.html
odoo/addons/partner_risk_insurance_product_sticker_invoice_report/tests/__init__.py
odoo/addons/partner_risk_insurance_product_sticker_invoice_report/tests/test_insurance_sticker.py
odoo/addons/partner_risk_insurance_product_sticker_invoice_report/views/credit_policy_company_view.xml
odoo/addons/partner_risk_insurance_product_sticker_invoice_report/views/product_sticker_view.xml
odoo_addon_partner_risk_insurance_product_sticker_invoice_report-18.0.1.0.1.dist-info/METADATA
odoo_addon_partner_risk_insurance_product_sticker_invoice_report-18.0.1.0.1.dist-info/WHEEL
odoo_addon_partner_risk_insurance_product_sticker_invoice_report-18.0.1.0.1.dist-info/top_level.txt
odoo_addon_partner_risk_insurance_product_sticker_invoice_report-18.0.1.0.1.dist-info/RECORD
