Metadata-Version: 2.1
Name: odoo-addon-partner_risk_insurance_product_sticker_invoice_report
Version: 18.0.1.0.1
Requires-Python: >=3.10
Requires-Dist: odoo-addon-account_invoice_report_product_sticker==18.0.*
Requires-Dist: odoo-addon-partner_risk_insurance==18.0.*
Requires-Dist: odoo==18.0.*
Summary: Display a Sticker on Invoice Reports secured with Risk Insurance
Home-page: https://github.com/OCA/credit-control
License: AGPL-3
Author: Moduon, Odoo Community Association (OCA)
Author-email: support@odoo-community.org
Classifier: Programming Language :: Python
Classifier: Framework :: Odoo
Classifier: Framework :: Odoo :: 18.0
Classifier: License :: OSI Approved :: GNU Affero General Public License v3
Classifier: Development Status :: 3 - Alpha
